{
    "ID": 55348,
    "name": "Arlington Central School District Board of Education v. Murphy",
    "href": "https:\/\/api.oyez.org\/cases\/2005\/05-18",
    "docket_number": "05-18",
    "additional_docket_numbers": null,
    "manner_of_jurisdiction": "Writ of \u003Ci\u003Ecertiorari\u003C\/i\u003E",
    "first_party": "Arlington Central School District Board of Education",
    "second_party": "Pearl Murphy, et vir.",
    "timeline": [
        {
            "event": "Granted",
            "dates": [
                1136527200
            ],
            "href": "https:\/\/api.oyez.org\/case_timeline\/case_timeline\/39586"
        },
        {
            "event": "Argued",
            "dates": [
                1145422800
            ],
            "href": "https:\/\/api.oyez.org\/case_timeline\/case_timeline\/39587"
        },
        {
            "event": "Decided",
            "dates": [
                1151298000
            ],
            "href": "https:\/\/api.oyez.org\/case_timeline\/case_timeline\/39588"
        }
    ],
    "lower_court": {
        "ID": 7,
        "name": "United States Court of Appeals for the Second Circuit",
        "href": "https:\/\/api.oyez.org\/taxonomy\/term\/7"
    },
    "facts_of_the_case": "\u003Cp\u003EUsing the federal Individuals with Disabilities Education Act (IDEA), Joseph Murray\u0027s parents brought legal action to require the Arlington Central School District to pay for their son\u0027s private school tuition. After they prevailed, they sought reimbursement from the school district for fees they had paid to an educational consultant during the proceedings. They relied on an IDEA provision that allows courts to \u0022award reasonable attorneys\u0027 fees as part of the costs\u0022 to prevailing parents. The school district argued that under \u003Cem\u003ECrawford Fitting Co. v. J.T. Gibbons, Inc.\u003C\/em\u003E, 482 U.S. 437, and \u003Cem\u003EWest Virginia Univ. Hospitals, Inc. v. Casey\u003C\/em\u003E, 499 U.S. 83, expert fees can only be reimbursed when there is explicit authorization in the statute. Because the statute made no specific mention of expert fees, the school district argued, the fees could not be reimbursed. The federal district court and Second Circuit Court of Appeals disagreed, however, finding that a Congressional Conference Committee Report and a footnote in \u003Cem\u003ECasey\u003C\/em\u003E referencing it showed that IDEA was intended to authorize reimbursement of expert fees.\u003C\/p\u003E\n",
    "question": "\u003Cp\u003EDoes the Individuals with Disabilities Education Act permit parents to recover fees they pay to experts during legal actions against school districts?\u003C\/p\u003E\n",
    "conclusion": "\u003Cp\u003ENo. In a 6-to-3 decision authored by Justice Samuel Alito, the Supreme Court held that IDEA did not authorize reimbursement of expert fees. \u0022While authorizing the award of reasonable attorney\u0027s fees, the Act contains detailed provisions that are designed to ensure that such awards are indeed reasonable,\u0022 Justice Alito wrote. \u0022The absence of any comparable provisions relating to expert fees strongly suggests that recovery of expert fees is not authorized.\u0022 Justice Alito went on to write that the case was made even simpler by the fact that, as an exercise of Congress\u0027s Spending Clause power, any provision requiring reimbursement of expert fees would have had to be \u0022unambiguous,\u0022 which it clearly was not. Justice Ginsburg, who joined the majority in finding that expert fees were not covered, wrote separately to disagree with that portion of the opinion.\u003C\/p\u003E\n",
    "advocates": [
        {
            "advocate": {
                "ID": 39704,
                "name": "Raymond G. Kuntz",
                "href": "https:\/\/api.oyez.org\/people\/raymond_g_kuntz",
                "last_name": "Kuntz",
                "roles": null,
                "thumbnail": null,
                "length_of_service": 0,
                "identifier": "raymond_g_kuntz"
            },
            "advocate_description": "argued the cause for Petitioner",
            "href": "https:\/\/api.oyez.org\/case_advocate\/case_advocate\/19249"
        },
        {
            "advocate": {
                "ID": 21650,
                "name": "David C. Vladeck",
                "href": "https:\/\/api.oyez.org\/people\/david_c_vladeck",
                "last_name": "Vladeck",
                "roles": null,
                "thumbnail": null,
                "length_of_service": 0,
                "identifier": "david_c_vladeck"
            },
            "advocate_description": "argued the cause for Respondents",
            "href": "https:\/\/api.oyez.org\/case_advocate\/case_advocate\/19250"
        },
        {
            "advocate": {
                "ID": 21494,
                "name": "David B. Salmons",
                "href": "https:\/\/api.oyez.org\/people\/david_b_salmons",
                "last_name": "Salmons",
                "roles": null,
                "thumbnail": null,
                "length_of_service": 0,
                "identifier": "david_b_salmons"
            },
            "advocate_description": "argued the cause for Petitioner",
            "href": "https:\/\/api.oyez.org\/case_advocate\/case_advocate\/19251"
        }
    ],
    "oral_argument_audio": [
        {
            "id": 22732,
            "title": "Oral Argument - April 19, 2006",
            "public_note": null,
            "unavailable": null,
            "href": "https:\/\/api.oyez.org\/case_media\/oral_argument_audio\/22732"
        }
    ],
    "citation": {
        "volume": "548",
        "page": "291",
        "year": "2006",
        "href": "https:\/\/api.oyez.org\/case_citation\/case_citation\/20628"
    },
    "decisions": [
        {
            "description": null,
            "votes": [
                {
                    "member": {
                        "ID": 15060,
                        "name": "John Paul Stevens",
                        "href": "https:\/\/api.oyez.org\/people\/john_paul_stevens",
                        "last_name": "Stevens",
                        "roles": [
                            {
                                "id": 2704,
                                "type": "scotus_justice",
                                "date_start": 188200800,
                                "date_end": 1277787600,
                                "appointing_president": "Gerald Ford",
                                "role_title": "Associate Justice of the Supreme Court of the United States",
                                "institution_name": "Supreme Court of the United States",
                                "href": "https:\/\/api.oyez.org\/preson_role\/scotus_justice\/2704"
                            }
                        ],
                        "thumbnail": {
                            "id": 32732,
                            "mime": "image\/png",
                            "size": 62101,
                            "href": "https:\/\/api.oyez.org\/sites\/default\/files\/john_paul_stevens.png"
                        },
                        "length_of_service": 12611,
                        "identifier": "john_paul_stevens"
                    },
                    "vote": "minority",
                    "opinion_type": "none",
                    "joining": [
                        {
                            "ID": 15139,
                            "name": "Stephen G. Breyer",
                            "href": "https:\/\/api.oyez.org\/people\/stephen_g_breyer",
                            "last_name": "Breyer",
                            "roles": [
                                {
                                    "id": 2785,
                                    "type": "scotus_justice",
                                    "date_start": 775890000,
                                    "date_end": 0,
                                    "appointing_president": "Bill Clinton",
                                    "role_title": "Associate Justice of the Supreme Court of the United States",
                                    "institution_name": "Supreme Court of the United States",
                                    "href": "https:\/\/api.oyez.org\/preson_role\/scotus_justice\/2785"
                                }
                            ],
                            "thumbnail": {
                                "id": 32682,
                                "mime": "image\/png",
                                "size": 49908,
                                "href": "https:\/\/api.oyez.org\/sites\/default\/files\/stephen_g_breyer_0.png"
                            },
                            "length_of_service": 7777,
                            "identifier": "stephen_g_breyer"
                        }
                    ],
                    "seniority": 2,
                    "ideology": -2.469,
                    "href": "https:\/\/api.oyez.org\/decision_vote\/decision_vote\/178590"
                },
                {
                    "member": {
                        "ID": 15049,
                        "name": "Antonin Scalia",
                        "href": "https:\/\/api.oyez.org\/people\/antonin_scalia",
                        "last_name": "Scalia",
                        "roles": [
                            {
                                "id": 2693,
                                "type": "scotus_justice",
                                "date_start": 528094800,
                                "date_end": 0,
                                "appointing_president": "Ronald Reagan",
                                "role_title": "Associate Justice of the Supreme Court of the United States",
                                "institution_name": "Supreme Court of the United States",
                                "href": "https:\/\/api.oyez.org\/preson_role\/scotus_justice\/2693"
                            }
                        ],
                        "thumbnail": {
                            "id": 32678,
                            "mime": "image\/png",
                            "size": 58944,
                            "href": "https:\/\/api.oyez.org\/sites\/default\/files\/antonin_scalia_0.png"
                        },
                        "length_of_service": 10699,
                        "identifier": "antonin_scalia"
                    },
                    "vote": "majority",
                    "opinion_type": "none",
                    "joining": null,
                    "seniority": 3,
                    "ideology": 2.579,
                    "href": "https:\/\/api.oyez.org\/decision_vote\/decision_vote\/178591"
                },
                {
                    "member": {
                        "ID": 15113,
                        "name": "Anthony M. Kennedy",
                        "href": "https:\/\/api.oyez.org\/people\/anthony_m_kennedy",
                        "last_name": "Kennedy",
                        "roles": [
                            {
                                "id": 2757,
                                "type": "scotus_justice",
                                "date_start": 572162400,
                                "date_end": 0,
                                "appointing_president": "Ronald Reagan",
                                "role_title": "Associate Justice of the Supreme Court of the United States",
                                "institution_name": "Supreme Court of the United States",
                                "href": "https:\/\/api.oyez.org\/preson_role\/scotus_justice\/2757"
                            }
                        ],
                        "thumbnail": {
                            "id": 32679,
                            "mime": "image\/png",
                            "size": 47100,
                            "href": "https:\/\/api.oyez.org\/sites\/default\/files\/anthony_kennedy_1_3.png"
                        },
                        "length_of_service": 10147,
                        "identifier": "anthony_m_kennedy"
                    },
                    "vote": "majority",
                    "opinion_type": "none",
                    "joining": null,
                    "seniority": 4,
                    "ideology": 0.417,
                    "href": "https:\/\/api.oyez.org\/decision_vote\/decision_vote\/178592"
                },
                {
                    "member": {
                        "ID": 15042,
                        "name": "David H. Souter",
                        "href": "https:\/\/api.oyez.org\/people\/david_h_souter",
                        "last_name": "Souter",
                        "roles": [
                            {
                                "id": 2686,
                                "type": "scotus_justice",
                                "date_start": 655362000,
                                "date_end": 1246251600,
                                "appointing_president": "George H. W. Bush",
                                "role_title": "Associate Justice of the Supreme Court of the United States",
                                "institution_name": "Supreme Court of the United States",
                                "href": "https:\/\/api.oyez.org\/preson_role\/scotus_justice\/2686"
                            }
                        ],
                        "thumbnail": {
                            "id": 32703,
                            "mime": "image\/png",
                            "size": 42141,
                            "href": "https:\/\/api.oyez.org\/sites\/default\/files\/david_souter.png"
                        },
                        "length_of_service": 6839,
                        "identifier": "david_h_souter"
                    },
                    "vote": "minority",
                    "opinion_type": "dissent",
                    "joining": [
                        {
                            "ID": 15139,
                            "name": "Stephen G. Breyer",
                            "href": "https:\/\/api.oyez.org\/people\/stephen_g_breyer",
                            "last_name": "Breyer",
                            "roles": [
                                {
                                    "id": 2785,
                                    "type": "scotus_justice",
                                    "date_start": 775890000,
                                    "date_end": 0,
                                    "appointing_president": "Bill Clinton",
                                    "role_title": "Associate Justice of the Supreme Court of the United States",
                                    "institution_name": "Supreme Court of the United States",
                                    "href": "https:\/\/api.oyez.org\/preson_role\/scotus_justice\/2785"
                                }
                            ],
                            "thumbnail": {
                                "id": 32682,
                                "mime": "image\/png",
                                "size": 49908,
                                "href": "https:\/\/api.oyez.org\/sites\/default\/files\/stephen_g_breyer_0.png"
                            },
                            "length_of_service": 7777,
                            "identifier": "stephen_g_breyer"
                        }
                    ],
                    "seniority": 5,
                    "ideology": -1.598,
                    "href": "https:\/\/api.oyez.org\/decision_vote\/decision_vote\/178593"
                },
                {
                    "member": {
                        "ID": 15100,
                        "name": "Clarence Thomas",
                        "href": "https:\/\/api.oyez.org\/people\/clarence_thomas",
                        "last_name": "Thomas",
                        "roles": [
                            {
                                "id": 2744,
                                "type": "scotus_justice",
                                "date_start": 688194000,
                                "date_end": 0,
                                "appointing_president": "George H. W. Bush",
                                "role_title": "Associate Justice of the Supreme Court of the United States",
                                "institution_name": "Supreme Court of the United States",
                                "href": "https:\/\/api.oyez.org\/preson_role\/scotus_justice\/2744"
                            }
                        ],
                        "thumbnail": {
                            "id": 32680,
                            "mime": "image\/png",
                            "size": 49064,
                            "href": "https:\/\/api.oyez.org\/sites\/default\/files\/clarence_thomas.png"
                        },
                        "length_of_service": 8870,
                        "identifier": "clarence_thomas"
                    },
                    "vote": "majority",
                    "opinion_type": "none",
                    "joining": null,
                    "seniority": 6,
                    "ideology": 3.981,
                    "href": "https:\/\/api.oyez.org\/decision_vote\/decision_vote\/178594"
                },
                {
                    "member": {
                        "ID": 15084,
                        "name": "Ruth Bader Ginsburg",
                        "href": "https:\/\/api.oyez.org\/people\/ruth_bader_ginsburg",
                        "last_name": "Ginsburg",
                        "roles": [
                            {
                                "id": 2728,
                                "type": "scotus_justice",
                                "date_start": 744958800,
                                "date_end": 0,
                                "appointing_president": "Bill Clinton",
                                "role_title": "Associate Justice of the Supreme Court of the United States",
                                "institution_name": "Supreme Court of the United States",
                                "href": "https:\/\/api.oyez.org\/preson_role\/scotus_justice\/2728"
                            }
                        ],
                        "thumbnail": {
                            "id": 32681,
                            "mime": "image\/png",
                            "size": 45030,
                            "href": "https:\/\/api.oyez.org\/sites\/default\/files\/ruth_bader_ginsburg_1_0.png"
                        },
                        "length_of_service": 8135,
                        "identifier": "ruth_bader_ginsburg"
                    },
                    "vote": "majority",
                    "opinion_type": "special concurrence",
                    "joining": null,
                    "seniority": 7,
                    "ideology": -1.475,
                    "href": "https:\/\/api.oyez.org\/decision_vote\/decision_vote\/178595"
                },
                {
                    "member": {
                        "ID": 15139,
                        "name": "Stephen G. Breyer",
                        "href": "https:\/\/api.oyez.org\/people\/stephen_g_breyer",
                        "last_name": "Breyer",
                        "roles": [
                            {
                                "id": 2785,
                                "type": "scotus_justice",
                                "date_start": 775890000,
                                "date_end": 0,
                                "appointing_president": "Bill Clinton",
                                "role_title": "Associate Justice of the Supreme Court of the United States",
                                "institution_name": "Supreme Court of the United States",
                                "href": "https:\/\/api.oyez.org\/preson_role\/scotus_justice\/2785"
                            }
                        ],
                        "thumbnail": {
                            "id": 32682,
                            "mime": "image\/png",
                            "size": 49908,
                            "href": "https:\/\/api.oyez.org\/sites\/default\/files\/stephen_g_breyer_0.png"
                        },
                        "length_of_service": 7777,
                        "identifier": "stephen_g_breyer"
                    },
                    "vote": "minority",
                    "opinion_type": "dissent",
                    "joining": null,
                    "seniority": 8,
                    "ideology": -1.419,
                    "href": "https:\/\/api.oyez.org\/decision_vote\/decision_vote\/178596"
                },
                {
                    "member": {
                        "ID": 15086,
                        "name": "John G. Roberts, Jr.",
                        "href": "https:\/\/api.oyez.org\/people\/john_g_roberts_jr",
                        "last_name": "Roberts",
                        "roles": [
                            {
                                "id": 2730,
                                "type": "scotus_justice",
                                "date_start": 1127970000,
                                "date_end": 0,
                                "appointing_president": "George W. Bush",
                                "role_title": "Chief Justice of the United States",
                                "institution_name": "Supreme Court of the United States",
                                "href": "https:\/\/api.oyez.org\/preson_role\/scotus_justice\/2730"
                            }
                        ],
                        "thumbnail": {
                            "id": 32683,
                            "mime": "image\/png",
                            "size": 52305,
                            "href": "https:\/\/api.oyez.org\/sites\/default\/files\/john_g_roberts_jr_0.png"
                        },
                        "length_of_service": 3702,
                        "identifier": "john_g_roberts_jr"
                    },
                    "vote": "majority",
                    "opinion_type": "none",
                    "joining": null,
                    "seniority": 1,
                    "ideology": 1.513,
                    "href": "https:\/\/api.oyez.org\/decision_vote\/decision_vote\/178597"
                },
                {
                    "member": {
                        "ID": 15068,
                        "name": "Samuel A. Alito, Jr.",
                        "href": "https:\/\/api.oyez.org\/people\/samuel_alito_jr",
                        "last_name": "Alito",
                        "roles": [
                            {
                                "id": 2712,
                                "type": "scotus_justice",
                                "date_start": 1138687200,
                                "date_end": 0,
                                "appointing_president": "George W. Bush",
                                "role_title": "Associate Justice of the Supreme Court of the United States",
                                "institution_name": "Supreme Court of the United States",
                                "href": "https:\/\/api.oyez.org\/preson_role\/scotus_justice\/2712"
                            }
                        ],
                        "thumbnail": {
                            "id": 32684,
                            "mime": "image\/png",
                            "size": 44799,
                            "href": "https:\/\/api.oyez.org\/sites\/default\/files\/samuel_a_alito_jr_1.png"
                        },
                        "length_of_service": 3531,
                        "identifier": "samuel_alito_jr"
                    },
                    "vote": "majority",
                    "opinion_type": "none",
                    "joining": null,
                    "seniority": 9,
                    "ideology": 1.556,
                    "href": "https:\/\/api.oyez.org\/decision_vote\/decision_vote\/178598"
                }
            ],
            "majority_vote": 6,
            "minority_vote": 3,
            "winning_party": "Arlington Central School District Board of Education",
            "decision_type": "majority opinion",
            "href": "https:\/\/api.oyez.org\/case_decision\/case_decision\/13369"
        }
    ],
    "first_party_label": "Petitioner",
    "second_party_label": "Respondent",
    "heard_by": [
        {
            "ID": 15149,
            "name": "Roberts Court (2006-2009)",
            "href": "https:\/\/api.oyez.org\/courts\/roberts2",
            "members": [
                {
                    "ID": 15086,
                    "name": "John G. Roberts, Jr.",
                    "href": "https:\/\/api.oyez.org\/people\/john_g_roberts_jr",
                    "last_name": "Roberts",
                    "roles": [
                        {
                            "id": 2730,
                            "type": "scotus_justice",
                            "date_start": 1127970000,
                            "date_end": 0,
                            "appointing_president": "George W. Bush",
                            "role_title": "Chief Justice of the United States",
                            "institution_name": "Supreme Court of the United States",
                            "href": "https:\/\/api.oyez.org\/preson_role\/scotus_justice\/2730"
                        }
                    ],
                    "thumbnail": {
                        "id": 32683,
                        "mime": "image\/png",
                        "size": 52305,
                        "href": "https:\/\/api.oyez.org\/sites\/default\/files\/john_g_roberts_jr_0.png"
                    },
                    "length_of_service": 3702,
                    "identifier": "john_g_roberts_jr"
                },
                {
                    "ID": 15060,
                    "name": "John Paul Stevens",
                    "href": "https:\/\/api.oyez.org\/people\/john_paul_stevens",
                    "last_name": "Stevens",
                    "roles": [
                        {
                            "id": 2704,
                            "type": "scotus_justice",
                            "date_start": 188200800,
                            "date_end": 1277787600,
                            "appointing_president": "Gerald Ford",
                            "role_title": "Associate Justice of the Supreme Court of the United States",
                            "institution_name": "Supreme Court of the United States",
                            "href": "https:\/\/api.oyez.org\/preson_role\/scotus_justice\/2704"
                        }
                    ],
                    "thumbnail": {
                        "id": 32732,
                        "mime": "image\/png",
                        "size": 62101,
                        "href": "https:\/\/api.oyez.org\/sites\/default\/files\/john_paul_stevens.png"
                    },
                    "length_of_service": 12611,
                    "identifier": "john_paul_stevens"
                },
                {
                    "ID": 15049,
                    "name": "Antonin Scalia",
                    "href": "https:\/\/api.oyez.org\/people\/antonin_scalia",
                    "last_name": "Scalia",
                    "roles": [
                        {
                            "id": 2693,
                            "type": "scotus_justice",
                            "date_start": 528094800,
                            "date_end": 0,
                            "appointing_president": "Ronald Reagan",
                            "role_title": "Associate Justice of the Supreme Court of the United States",
                            "institution_name": "Supreme Court of the United States",
                            "href": "https:\/\/api.oyez.org\/preson_role\/scotus_justice\/2693"
                        }
                    ],
                    "thumbnail": {
                        "id": 32678,
                        "mime": "image\/png",
                        "size": 58944,
                        "href": "https:\/\/api.oyez.org\/sites\/default\/files\/antonin_scalia_0.png"
                    },
                    "length_of_service": 10699,
                    "identifier": "antonin_scalia"
                },
                {
                    "ID": 15113,
                    "name": "Anthony M. Kennedy",
                    "href": "https:\/\/api.oyez.org\/people\/anthony_m_kennedy",
                    "last_name": "Kennedy",
                    "roles": [
                        {
                            "id": 2757,
                            "type": "scotus_justice",
                            "date_start": 572162400,
                            "date_end": 0,
                            "appointing_president": "Ronald Reagan",
                            "role_title": "Associate Justice of the Supreme Court of the United States",
                            "institution_name": "Supreme Court of the United States",
                            "href": "https:\/\/api.oyez.org\/preson_role\/scotus_justice\/2757"
                        }
                    ],
                    "thumbnail": {
                        "id": 32679,
                        "mime": "image\/png",
                        "size": 47100,
                        "href": "https:\/\/api.oyez.org\/sites\/default\/files\/anthony_kennedy_1_3.png"
                    },
                    "length_of_service": 10147,
                    "identifier": "anthony_m_kennedy"
                },
                {
                    "ID": 15042,
                    "name": "David H. Souter",
                    "href": "https:\/\/api.oyez.org\/people\/david_h_souter",
                    "last_name": "Souter",
                    "roles": [
                        {
                            "id": 2686,
                            "type": "scotus_justice",
                            "date_start": 655362000,
                            "date_end": 1246251600,
                            "appointing_president": "George H. W. Bush",
                            "role_title": "Associate Justice of the Supreme Court of the United States",
                            "institution_name": "Supreme Court of the United States",
                            "href": "https:\/\/api.oyez.org\/preson_role\/scotus_justice\/2686"
                        }
                    ],
                    "thumbnail": {
                        "id": 32703,
                        "mime": "image\/png",
                        "size": 42141,
                        "href": "https:\/\/api.oyez.org\/sites\/default\/files\/david_souter.png"
                    },
                    "length_of_service": 6839,
                    "identifier": "david_h_souter"
                },
                {
                    "ID": 15100,
                    "name": "Clarence Thomas",
                    "href": "https:\/\/api.oyez.org\/people\/clarence_thomas",
                    "last_name": "Thomas",
                    "roles": [
                        {
                            "id": 2744,
                            "type": "scotus_justice",
                            "date_start": 688194000,
                            "date_end": 0,
                            "appointing_president": "George H. W. Bush",
                            "role_title": "Associate Justice of the Supreme Court of the United States",
                            "institution_name": "Supreme Court of the United States",
                            "href": "https:\/\/api.oyez.org\/preson_role\/scotus_justice\/2744"
                        }
                    ],
                    "thumbnail": {
                        "id": 32680,
                        "mime": "image\/png",
                        "size": 49064,
                        "href": "https:\/\/api.oyez.org\/sites\/default\/files\/clarence_thomas.png"
                    },
                    "length_of_service": 8870,
                    "identifier": "clarence_thomas"
                },
                {
                    "ID": 15084,
                    "name": "Ruth Bader Ginsburg",
                    "href": "https:\/\/api.oyez.org\/people\/ruth_bader_ginsburg",
                    "last_name": "Ginsburg",
                    "roles": [
                        {
                            "id": 2728,
                            "type": "scotus_justice",
                            "date_start": 744958800,
                            "date_end": 0,
                            "appointing_president": "Bill Clinton",
                            "role_title": "Associate Justice of the Supreme Court of the United States",
                            "institution_name": "Supreme Court of the United States",
                            "href": "https:\/\/api.oyez.org\/preson_role\/scotus_justice\/2728"
                        }
                    ],
                    "thumbnail": {
                        "id": 32681,
                        "mime": "image\/png",
                        "size": 45030,
                        "href": "https:\/\/api.oyez.org\/sites\/default\/files\/ruth_bader_ginsburg_1_0.png"
                    },
                    "length_of_service": 8135,
                    "identifier": "ruth_bader_ginsburg"
                },
                {
                    "ID": 15139,
                    "name": "Stephen G. Breyer",
                    "href": "https:\/\/api.oyez.org\/people\/stephen_g_breyer",
                    "last_name": "Breyer",
                    "roles": [
                        {
                            "id": 2785,
                            "type": "scotus_justice",
                            "date_start": 775890000,
                            "date_end": 0,
                            "appointing_president": "Bill Clinton",
                            "role_title": "Associate Justice of the Supreme Court of the United States",
                            "institution_name": "Supreme Court of the United States",
                            "href": "https:\/\/api.oyez.org\/preson_role\/scotus_justice\/2785"
                        }
                    ],
                    "thumbnail": {
                        "id": 32682,
                        "mime": "image\/png",
                        "size": 49908,
                        "href": "https:\/\/api.oyez.org\/sites\/default\/files\/stephen_g_breyer_0.png"
                    },
                    "length_of_service": 7777,
                    "identifier": "stephen_g_breyer"
                },
                {
                    "ID": 15068,
                    "name": "Samuel A. Alito, Jr.",
                    "href": "https:\/\/api.oyez.org\/people\/samuel_alito_jr",
                    "last_name": "Alito",
                    "roles": [
                        {
                            "id": 2712,
                            "type": "scotus_justice",
                            "date_start": 1138687200,
                            "date_end": 0,
                            "appointing_president": "George W. Bush",
                            "role_title": "Associate Justice of the Supreme Court of the United States",
                            "institution_name": "Supreme Court of the United States",
                            "href": "https:\/\/api.oyez.org\/preson_role\/scotus_justice\/2712"
                        }
                    ],
                    "thumbnail": {
                        "id": 32684,
                        "mime": "image\/png",
                        "size": 44799,
                        "href": "https:\/\/api.oyez.org\/sites\/default\/files\/samuel_a_alito_jr_1.png"
                    },
                    "length_of_service": 3531,
                    "identifier": "samuel_alito_jr"
                }
            ],
            "court_start": 1138687200,
            "images": [
                {
                    "id": 12234,
                    "mime": "image\/jpeg",
                    "size": 70439,
                    "href": "https:\/\/api.oyez.org\/sites\/default\/files\/images\/courts\/large\/roberts_court_2006-2009.jpg"
                }
            ],
            "identifier": "roberts2"
        }
    ],
    "decided_by": {
        "ID": 15149,
        "name": "Roberts Court (2006-2009)",
        "href": "https:\/\/api.oyez.org\/courts\/roberts2",
        "members": [
            {
                "ID": 15086,
                "name": "John G. Roberts, Jr.",
                "href": "https:\/\/api.oyez.org\/people\/john_g_roberts_jr",
                "last_name": "Roberts",
                "roles": [
                    {
                        "id": 2730,
                        "type": "scotus_justice",
                        "date_start": 1127970000,
                        "date_end": 0,
                        "appointing_president": "George W. Bush",
                        "role_title": "Chief Justice of the United States",
                        "institution_name": "Supreme Court of the United States",
                        "href": "https:\/\/api.oyez.org\/preson_role\/scotus_justice\/2730"
                    }
                ],
                "thumbnail": {
                    "id": 32683,
                    "mime": "image\/png",
                    "size": 52305,
                    "href": "https:\/\/api.oyez.org\/sites\/default\/files\/john_g_roberts_jr_0.png"
                },
                "length_of_service": 3702,
                "identifier": "john_g_roberts_jr"
            },
            {
                "ID": 15060,
                "name": "John Paul Stevens",
                "href": "https:\/\/api.oyez.org\/people\/john_paul_stevens",
                "last_name": "Stevens",
                "roles": [
                    {
                        "id": 2704,
                        "type": "scotus_justice",
                        "date_start": 188200800,
                        "date_end": 1277787600,
                        "appointing_president": "Gerald Ford",
                        "role_title": "Associate Justice of the Supreme Court of the United States",
                        "institution_name": "Supreme Court of the United States",
                        "href": "https:\/\/api.oyez.org\/preson_role\/scotus_justice\/2704"
                    }
                ],
                "thumbnail": {
                    "id": 32732,
                    "mime": "image\/png",
                    "size": 62101,
                    "href": "https:\/\/api.oyez.org\/sites\/default\/files\/john_paul_stevens.png"
                },
                "length_of_service": 12611,
                "identifier": "john_paul_stevens"
            },
            {
                "ID": 15049,
                "name": "Antonin Scalia",
                "href": "https:\/\/api.oyez.org\/people\/antonin_scalia",
                "last_name": "Scalia",
                "roles": [
                    {
                        "id": 2693,
                        "type": "scotus_justice",
                        "date_start": 528094800,
                        "date_end": 0,
                        "appointing_president": "Ronald Reagan",
                        "role_title": "Associate Justice of the Supreme Court of the United States",
                        "institution_name": "Supreme Court of the United States",
                        "href": "https:\/\/api.oyez.org\/preson_role\/scotus_justice\/2693"
                    }
                ],
                "thumbnail": {
                    "id": 32678,
                    "mime": "image\/png",
                    "size": 58944,
                    "href": "https:\/\/api.oyez.org\/sites\/default\/files\/antonin_scalia_0.png"
                },
                "length_of_service": 10699,
                "identifier": "antonin_scalia"
            },
            {
                "ID": 15113,
                "name": "Anthony M. Kennedy",
                "href": "https:\/\/api.oyez.org\/people\/anthony_m_kennedy",
                "last_name": "Kennedy",
                "roles": [
                    {
                        "id": 2757,
                        "type": "scotus_justice",
                        "date_start": 572162400,
                        "date_end": 0,
                        "appointing_president": "Ronald Reagan",
                        "role_title": "Associate Justice of the Supreme Court of the United States",
                        "institution_name": "Supreme Court of the United States",
                        "href": "https:\/\/api.oyez.org\/preson_role\/scotus_justice\/2757"
                    }
                ],
                "thumbnail": {
                    "id": 32679,
                    "mime": "image\/png",
                    "size": 47100,
                    "href": "https:\/\/api.oyez.org\/sites\/default\/files\/anthony_kennedy_1_3.png"
                },
                "length_of_service": 10147,
                "identifier": "anthony_m_kennedy"
            },
            {
                "ID": 15042,
                "name": "David H. Souter",
                "href": "https:\/\/api.oyez.org\/people\/david_h_souter",
                "last_name": "Souter",
                "roles": [
                    {
                        "id": 2686,
                        "type": "scotus_justice",
                        "date_start": 655362000,
                        "date_end": 1246251600,
                        "appointing_president": "George H. W. Bush",
                        "role_title": "Associate Justice of the Supreme Court of the United States",
                        "institution_name": "Supreme Court of the United States",
                        "href": "https:\/\/api.oyez.org\/preson_role\/scotus_justice\/2686"
                    }
                ],
                "thumbnail": {
                    "id": 32703,
                    "mime": "image\/png",
                    "size": 42141,
                    "href": "https:\/\/api.oyez.org\/sites\/default\/files\/david_souter.png"
                },
                "length_of_service": 6839,
                "identifier": "david_h_souter"
            },
            {
                "ID": 15100,
                "name": "Clarence Thomas",
                "href": "https:\/\/api.oyez.org\/people\/clarence_thomas",
                "last_name": "Thomas",
                "roles": [
                    {
                        "id": 2744,
                        "type": "scotus_justice",
                        "date_start": 688194000,
                        "date_end": 0,
                        "appointing_president": "George H. W. Bush",
                        "role_title": "Associate Justice of the Supreme Court of the United States",
                        "institution_name": "Supreme Court of the United States",
                        "href": "https:\/\/api.oyez.org\/preson_role\/scotus_justice\/2744"
                    }
                ],
                "thumbnail": {
                    "id": 32680,
                    "mime": "image\/png",
                    "size": 49064,
                    "href": "https:\/\/api.oyez.org\/sites\/default\/files\/clarence_thomas.png"
                },
                "length_of_service": 8870,
                "identifier": "clarence_thomas"
            },
            {
                "ID": 15084,
                "name": "Ruth Bader Ginsburg",
                "href": "https:\/\/api.oyez.org\/people\/ruth_bader_ginsburg",
                "last_name": "Ginsburg",
                "roles": [
                    {
                        "id": 2728,
                        "type": "scotus_justice",
                        "date_start": 744958800,
                        "date_end": 0,
                        "appointing_president": "Bill Clinton",
                        "role_title": "Associate Justice of the Supreme Court of the United States",
                        "institution_name": "Supreme Court of the United States",
                        "href": "https:\/\/api.oyez.org\/preson_role\/scotus_justice\/2728"
                    }
                ],
                "thumbnail": {
                    "id": 32681,
                    "mime": "image\/png",
                    "size": 45030,
                    "href": "https:\/\/api.oyez.org\/sites\/default\/files\/ruth_bader_ginsburg_1_0.png"
                },
                "length_of_service": 8135,
                "identifier": "ruth_bader_ginsburg"
            },
            {
                "ID": 15139,
                "name": "Stephen G. Breyer",
                "href": "https:\/\/api.oyez.org\/people\/stephen_g_breyer",
                "last_name": "Breyer",
                "roles": [
                    {
                        "id": 2785,
                        "type": "scotus_justice",
                        "date_start": 775890000,
                        "date_end": 0,
                        "appointing_president": "Bill Clinton",
                        "role_title": "Associate Justice of the Supreme Court of the United States",
                        "institution_name": "Supreme Court of the United States",
                        "href": "https:\/\/api.oyez.org\/preson_role\/scotus_justice\/2785"
                    }
                ],
                "thumbnail": {
                    "id": 32682,
                    "mime": "image\/png",
                    "size": 49908,
                    "href": "https:\/\/api.oyez.org\/sites\/default\/files\/stephen_g_breyer_0.png"
                },
                "length_of_service": 7777,
                "identifier": "stephen_g_breyer"
            },
            {
                "ID": 15068,
                "name": "Samuel A. Alito, Jr.",
                "href": "https:\/\/api.oyez.org\/people\/samuel_alito_jr",
                "last_name": "Alito",
                "roles": [
                    {
                        "id": 2712,
                        "type": "scotus_justice",
                        "date_start": 1138687200,
                        "date_end": 0,
                        "appointing_president": "George W. Bush",
                        "role_title": "Associate Justice of the Supreme Court of the United States",
                        "institution_name": "Supreme Court of the United States",
                        "href": "https:\/\/api.oyez.org\/preson_role\/scotus_justice\/2712"
                    }
                ],
                "thumbnail": {
                    "id": 32684,
                    "mime": "image\/png",
                    "size": 44799,
                    "href": "https:\/\/api.oyez.org\/sites\/default\/files\/samuel_a_alito_jr_1.png"
                },
                "length_of_service": 3531,
                "identifier": "samuel_alito_jr"
            }
        ],
        "court_start": 1138687200,
        "images": [
            {
                "id": 12234,
                "mime": "image\/jpeg",
                "size": 70439,
                "href": "https:\/\/api.oyez.org\/sites\/default\/files\/images\/courts\/large\/roberts_court_2006-2009.jpg"
            }
        ],
        "identifier": "roberts2"
    },
    "term": "2005",
    "location": null,
    "opinion_announcement": [
        {
            "id": 21335,
            "title": "Opinion Announcement - June 26, 2006",
            "unavailable": null,
            "href": "https:\/\/api.oyez.org\/case_media\/opinion_announcement_audio\/21335"
        }
    ],
    "description": null,
    "written_opinion": null,
    "related_cases": null
}