{
    "id": 20495,
    "title": "Opinion Announcement - April 05, 1999",
    "transcript": {
        "title": "Mitchell v. United States",
        "duration": 157.896,
        "sections": [
            {
                "start": 0,
                "stop": 157.896,
                "byte_start": 86220,
                "byte_stop": 717756,
                "turns": [
                    {
                        "start": 0,
                        "stop": 157.896,
                        "byte_start": 86220,
                        "byte_stop": 717756,
                        "speaker": {
                            "ID": 15141,
                            "name": "William H. Rehnquist",
                            "href": "https:\/\/api.oyez.org\/people\/william_h_rehnquist",
                            "last_name": "Rehnquist",
                            "roles": [
                                {
                                    "id": 2787,
                                    "type": "scotus_justice",
                                    "date_start": 63612000,
                                    "date_end": 528094800,
                                    "appointing_president": "Richard Nixon",
                                    "role_title": "Associate Justice of the Supreme Court of the United States",
                                    "institution_name": "Supreme Court of the United States",
                                    "href": "https:\/\/api.oyez.org\/preson_role\/scotus_justice\/2787"
                                },
                                {
                                    "id": 2788,
                                    "type": "scotus_justice",
                                    "date_start": 528094800,
                                    "date_end": 1125723600,
                                    "appointing_president": "Ronald Reagan",
                                    "role_title": "Chief Justice of the United States",
                                    "institution_name": "Supreme Court of the United States",
                                    "href": "https:\/\/api.oyez.org\/preson_role\/scotus_justice\/2788"
                                }
                            ],
                            "thumbnail": {
                                "id": 32786,
                                "mime": "image\/png",
                                "size": 46923,
                                "href": "https:\/\/api.oyez.org\/sites\/default\/files\/william_rehnquist.png"
                            },
                            "length_of_service": 12293,
                            "identifier": "william_h_rehnquist"
                        },
                        "text_blocks": [
                            {
                                "start": 0,
                                "stop": 3.092,
                                "byte_start": 86220,
                                "byte_stop": 98654,
                                "text": "I have the opinions of the Court to announce in three cases."
                            },
                            {
                                "start": 3.092,
                                "stop": 9.395,
                                "byte_start": 98654,
                                "byte_stop": 123836,
                                "text": "The first is 97-7541, Amanda Mitchell versus United States."
                            },
                            {
                                "start": 9.395,
                                "stop": 20.356,
                                "byte_start": 123836,
                                "byte_stop": 167722,
                                "text": "Now, the petitioner Amanda Mitchell pleaded guilty to conspiracy to distribute cocaine, but reserve the right to contest the amount of drugs attributable to her at sentencing."
                            },
                            {
                                "start": 20.356,
                                "stop": 30.05,
                                "byte_start": 167722,
                                "byte_stop": 206488,
                                "text": "The sentencing hearing witnesses for the government testified that the amounts of drugs were substantial and Mitchell distributed this without taking the stand to testify."
                            },
                            {
                                "start": 30.05,
                                "stop": 33.5,
                                "byte_start": 206488,
                                "byte_stop": 220280,
                                "text": "The District Court ruled that is a consequence of her guilty plea."
                            },
                            {
                                "start": 33.5,
                                "stop": 38.25,
                                "byte_start": 220280,
                                "byte_stop": 239298,
                                "text": "Mitchell had no rights to remain silent with respect to the details of her crimes."
                            },
                            {
                                "start": 38.25,
                                "stop": 46.838,
                                "byte_start": 239298,
                                "byte_stop": 273675,
                                "text": "In imposing a 10-year sentence the judge told Mitchell that he held it against her but she did not come forward and explained her side of the dispute."
                            },
                            {
                                "start": 46.838,
                                "stop": 55.165,
                                "byte_start": 273675,
                                "byte_stop": 306902,
                                "text": "The Court of Appeals for the Third Circuit affirmed the sentence and held it by pleading guilty to the offense Mitchell have waived her Fifth Amendment privilege."
                            },
                            {
                                "start": 55.165,
                                "stop": 63.141,
                                "byte_start": 306902,
                                "byte_stop": 338876,
                                "text": "In an opinion authored by Justice Kennedy we hold that a guilty plea is not a waiver of the Fifth Amendment privilege at the sentencing."
                            },
                            {
                                "start": 63.141,
                                "stop": 74.403,
                                "byte_start": 338876,
                                "byte_stop": 383911,
                                "text": "It is well-established that a witness in a single proceeding may not testify voluntarily about a subject and then invoke the privilege against self-incrimination when questioned about the details."
                            },
                            {
                                "start": 74.403,
                                "stop": 83.793,
                                "byte_start": 383911,
                                "byte_stop": 421423,
                                "text": "That is because a witness cannot pick and choose what aspects of a particular subject to discuss without casting doubt on the trustworthiness of the statement."
                            },
                            {
                                "start": 83.793,
                                "stop": 92.888,
                                "byte_start": 421423,
                                "byte_stop": 457786,
                                "text": "The concerns which justify requiring the defendant to undergo cross-examination when he or she testifies are absent at a plea colloquy, however."
                            },
                            {
                                "start": 92.888,
                                "stop": 103.785,
                                "byte_start": 457786,
                                "byte_stop": 501462,
                                "text": "Instead of presenting testimony that puts facts into dispute the defendant who pleads guilty takes matters out of dispute often by confirming the prosecutions version of the facts."
                            },
                            {
                                "start": 103.785,
                                "stop": 116.834,
                                "byte_start": 501462,
                                "byte_stop": 553603,
                                "text": "Under these circumstances there is little danger that the court will be misled by selective disclosure, nor does the federal rule of Criminal Procedure 11 which governs pleas contemplate the broad waiver of the privilege."
                            },
                            {
                                "start": 116.834,
                                "stop": 122.487,
                                "byte_start": 553603,
                                "byte_stop": 576173,
                                "text": "Treating a guilty plea as a waiver of the privilege at sentencing would encroach on the rights of defendants."
                            },
                            {
                                "start": 122.487,
                                "stop": 134.829,
                                "byte_start": 576173,
                                "byte_stop": 625596,
                                "text": "Were we to accept the government\u2019s position prosecutors could indict without specifying the quantity of drugs involved, obtain a guilty plea, and then put the defendant on the stand of sentencing to fill in the drug quantity."
                            },
                            {
                                "start": 134.829,
                                "stop": 145.984,
                                "byte_start": 625596,
                                "byte_stop": 670213,
                                "text": "We also hold that the District Court was not entitled based on Mitchell\u2019s silence to draw an adverse inference with regard to the amount of drugs attributable to her."
                            },
                            {
                                "start": 145.984,
                                "stop": 157.896,
                                "byte_start": 670213,
                                "byte_stop": 717756,
                                "text": "Justice Scalia has filed a dissenting opinion which has been joined by Justice O\u2019Connor, Justice Thomas, and me; Justice Thomas has also filed a dissenting opinion."
                            }
                        ]
                    }
                ]
            }
        ]
    },
    "media_file": [
        {
            "id": 50114,
            "mime": "audio\/mpeg",
            "size": 718070,
            "href": "https:\/\/s3.amazonaws.com\/oyez.case-media.mp3\/case_data\/1998\/97-7541\/19990405o_97-7541.delivery.mp3"
        },
        {
            "id": 71904,
            "mime": "audio\/ogg",
            "size": 1601500,
            "href": "https:\/\/s3.amazonaws.com\/oyez.case-media.ogg\/case_data\/1998\/97-7541\/19990405o_97-7541.ogg"
        },
        {
            "id": 71905,
            "mime": "application\/x-mpegURL",
            "size": 2443,
            "href": "https:\/\/s3.amazonaws.com\/oyez.case-media.hls\/case_data\/1998\/97-7541\/19990405o_97-7541.m3u8"
        }
    ],
    "damaged": null,
    "unavailable": null
}